{
	"name": "pl_cdc_tst_csv",
	"properties": {
		"activities": [
			{
				"name": "dataflow2",
				"type": "ExecuteDataFlow",
				"dependsOn": [],
				"policy": {
					"timeout": "0.12:00:00",
					"retry": 0,
					"retryIntervalInSeconds": 30,
					"secureOutput": false,
					"secureInput": false
				},
				"userProperties": [],
				"typeProperties": {
					"dataflow": {
						"referenceName": "dataflow2",
						"type": "DataFlowReference"
					},
					"compute": {
						"coreCount": 8,
						"computeType": "General"
					},
					"traceLevel": "Fine",
					"continuationSettings": {
						"customizedCheckpointKey": "771695b5-ac4f-4afe-8762-19e453f50a8b"
					}
				}
			}
		],
		"annotations": []
	}
}